{
        "key": "504b2e16a99b299085d91212",
        "addrs": [
                {
                        "addr": {
                                "id": "5ebd7766192a47e308a6b1f8ac0b704023b82173",
                                "ip": "144.76.102.71",
                                "port": 26656
                        },
                        "src": {
                                "id": "c9c11d64c80034d30521e61e290cdfbe33a0bc10",
                                "ip": "135.181.245.48",
                                "port": 26656
                        },
                        "buckets": [
                                34
                        ],
                        "attempts": 0,
                        "bucket_type": 2,
                        "last_attempt": "2024-04-03T21:58:57.461558918+03:00",
                        "last_success": "2024-04-03T21:58:57.461558918+03:00",
                        "last_ban_time": "0001-01-01T00:00:00Z"
                }
        ]
}

